{
  "room001": {
    "description": [
      "You are standing at the entrance to the dungeon.",
      "The cold, misty air bites at your cheeks as the chill wind whips at your cloak."
    ],
    "exits": [
      {
        "name": "NORTH",
        "door": "main_dungeon_door",
        "destination": "room002",
        "description": "The yawing mouth of the maze is before you. The air as black an thick as tar."
      },
      {
        "name": "SOUTH",
        "locked": false,
        "destination": "room003",
        "description": "Behind you, to the south, are rolling fields and the way back home."
      }
    ]
  },
  "room002": {
    "description": [
      "You have successfully made it through this single room puzzle. Good for you, champ!"
    ],
    "roomInventory": [],
    "exits": []
  },
  "room003": {
    "description": [
      "You turn to face the setting sun, your fight will wait for another day."
    ],
    "roomInventory": [],
    "exits": [
      {
        "name": "NORTH",
        "destination": "room001",
        "unlockedDescription": "To the north of you is the intimidating castle zanbar.",
        "locked": false
      }
    ]
  }
}